ai_assist_utils/__init__.py
ai_assist_utils/core.py
ai_assist_utils-0.3.1.dist-info/licenses/LICENSE
ai_assist_utils-0.3.1.dist-info/METADATA
ai_assist_utils-0.3.1.dist-info/WHEEL
ai_assist_utils-0.3.1.dist-info/top_level.txt
ai_assist_utils-0.3.1.dist-info/RECORD
