Metadata-Version: 2.4
Name: ai_assist_utils
Version: 0.3.1
Summary: AI helper utilities for Gemini
Author: Your Name
License: MIT
Project-URL: Homepage, https://pypi.org/project/ai-assist-utils/
Project-URL: Source, https://github.com/yourrepo
Requires-Python: >=3.8
License-File: LICENSE
Dynamic: license-file
